Metadata-Version: 1.0
Name: dsbn-distributions
Version: 0.1
Summary: Gaussian distributions
Home-page: UNKNOWN
Author: P. Dinagaran
Author-email: UNKNOWN
License: UNKNOWN
Platform: UNKNOWN
